streamlit_tree_independent_components/__init__.py
streamlit_tree_independent_components/example.py
streamlit_tree_independent_components/frontend/build/asset-manifest.json
streamlit_tree_independent_components/frontend/build/bootstrap.min.css
streamlit_tree_independent_components/frontend/build/index.html
streamlit_tree_independent_components/frontend/build/static/css/main.00fe4333.css
streamlit_tree_independent_components/frontend/build/static/css/main.00fe4333.css.map
streamlit_tree_independent_components/frontend/build/static/css/main.05f62868.css
streamlit_tree_independent_components/frontend/build/static/css/main.05f62868.css.map
streamlit_tree_independent_components/frontend/build/static/css/main.24ad1021.css
streamlit_tree_independent_components/frontend/build/static/css/main.24ad1021.css.map
streamlit_tree_independent_components/frontend/build/static/css/main.315d2e85.css
streamlit_tree_independent_components/frontend/build/static/css/main.315d2e85.css.map
streamlit_tree_independent_components/frontend/build/static/css/main.5ea73328.css
streamlit_tree_independent_components/frontend/build/static/css/main.5ea73328.css.map
streamlit_tree_independent_components/frontend/build/static/css/main.d341adaf.css
streamlit_tree_independent_components/frontend/build/static/css/main.d341adaf.css.map
streamlit_tree_independent_components/frontend/build/static/js/main.34b209ff.js
streamlit_tree_independent_components/frontend/build/static/js/main.34b209ff.js.LICENSE.txt
streamlit_tree_independent_components/frontend/build/static/js/main.34b209ff.js.map
streamlit_tree_independent_components/frontend/build/static/js/main.5bcfa681.js
streamlit_tree_independent_components/frontend/build/static/js/main.5bcfa681.js.LICENSE.txt
streamlit_tree_independent_components/frontend/build/static/js/main.5bcfa681.js.map
streamlit_tree_independent_components/frontend/build/static/js/main.61fc814b.js
streamlit_tree_independent_components/frontend/build/static/js/main.61fc814b.js.LICENSE.txt
streamlit_tree_independent_components-0.3.1.dist-info/LICENSE
streamlit_tree_independent_components-0.3.1.dist-info/METADATA
streamlit_tree_independent_components-0.3.1.dist-info/WHEEL
streamlit_tree_independent_components-0.3.1.dist-info/top_level.txt
streamlit_tree_independent_components-0.3.1.dist-info/RECORD
